LICENSE
MANIFEST.in
README.rst
setup.py
PedalPi_WebService.egg-info/PKG-INFO
PedalPi_WebService.egg-info/SOURCES.txt
PedalPi_WebService.egg-info/dependency_links.txt
PedalPi_WebService.egg-info/requires.txt
PedalPi_WebService.egg-info/top_level.txt
webservice/__init__.py
webservice/properties.py
webservice/webservice.py
webservice/handler/__init__.py
webservice/handler/abstract_request_handler.py
webservice/handler/bank_handler.py
webservice/handler/banks_handler.py
webservice/handler/component_data_handler.py
webservice/handler/connection_handler.py
webservice/handler/current_data_handler.py
webservice/handler/current_effect_status_handler.py
webservice/handler/current_handler.py
webservice/handler/current_pedalboard_handler.py
webservice/handler/device_name_handler.py
webservice/handler/effect_handler.py
webservice/handler/move_bank_handler.py
webservice/handler/move_pedalboard_handler.py
webservice/handler/param_handler.py
webservice/handler/pedalboard_data_handler.py
webservice/handler/pedalboard_handler.py
webservice/handler/plugin_handler.py
webservice/handler/plugins_handler.py
webservice/handler/plugins_reload_handler.py
webservice/search/__init__.py
webservice/search/abstract_zeroconf_service.py
webservice/search/pybonjour_service.py
webservice/search/zeroconf_factory.py
webservice/search/zeroconf_service.py
webservice/util/__init__.py
webservice/util/handler_utils.py
webservice/websocket/__init__.py
webservice/websocket/web_socket_connection_handler.py
webservice/websocket/web_socket_connections.py
webservice/websocket/websocket_connection_observer.py