Metadata-Version: 1.1
Name: PedalPi-WebService
Version: 0.3.0
Summary: WebService (REST and WebSocket) to access and controller your Pedal Pi pedals set configurations
Home-page: https://github.com/PedalPi/WebService
Author: Paulo Mateus Moura da Silva (SrMouraSilva)
Author-email: mateus.moura@hotmail.com
License: Apache Software License v2
Keywords: pedal-pi mod-host lv2 audio plugins-manager pedal-pi-component
Platform: Linux
Classifier: Development Status :: 3 - Alpha
Classifier: Intended Audience :: Developers
Classifier: License :: OSI Approved :: Apache Software License
Classifier: Topic :: Multimedia :: Sound/Audio
Classifier: Programming Language :: Python :: 3.4
Classifier: Programming Language :: Python :: 3.5
Classifier: Programming Language :: Python :: 3.6
